[
    {
        "UserId": "None",
        "ProjectsStorageID": "None",
        "ProjectId": "None",
        "ProjectName": "None",
        "Content": "Body",
        "Language": "Ko",
        "TaskName": ["BodySplit" ,"IndexDefine"],
        "IndexCount": 0,
        "BodyCount": 0,
        "ChunkCount": 0,
        "Completion": "No",
        "Memo": "Bodys가 테스크별로 다양한 토큰이 필요한 경우 다양한 토큰으로 구성하기, 예시: Bodys(2000), Bodys(3000)"
    },
    {
        "SplitedBodyScripts": [
            {
                "IndexId": 0,
                "IndexTag": "None",
                "Index": "None",
                "BodyId": 0,
                "SplitedBodyChunks": [
                    {
                        "ChunkId": 0,
                        "Tag": "None",
                        "Chunk": "None"
                    }
                ]
            }
        ]
    },
    {
        "Bodys": [
            {
                "BodyId": 0,
                "ChunkId": [],
                "Task": [],
                "Body": "None",
                "Correction": "None",
                "Character": "None",
                "Context": "None"
            }
        ]
    }
]